[
  {
    "name": "143488691",
    "status": "Available",
    "isActive": "true",
    "domain": "CORE",
    "type": "CI"
  },
  {
    "name": "164125488",
    "status": "Expired",
    "isActive": "false",
    "domain": "CORE",
    "type": "CI"
  },
  {
    "name": "303590885",
    "status": "InProgress",
    "isActive": "true",
    "domain": "CORE",
    "type": "CI"
  },
  {
    "name": "328158359",
    "status": "Expired",
    "isActive": "false",
    "domain": "CORE",
    "type": "CI"
  },
  {
    "name": "336740161",
    "status": "Expired",
    "isActive": "false",
    "domain": "CORE",
    "type": "CI"
  },
  {
    "name": "385103637",
    "status": "Expired",
    "isActive": "false",
    "domain": "CORE",
    "type": "CI"
  },
  {
    "name": "424330982",
    "status": "Expired",
    "isActive": "false",
    "domain": "CORE",
    "type": "CI"
  },
  {
    "name": "445119872",
    "status": "Expired",
    "isActive": "false",
    "domain": "CORE",
    "type": "CI"
  },
  {
    "name": "589431377",
    "status": "InProgress",
    "isActive": "true",
    "domain": "CORE",
    "type": "CI"
  },
  {
    "name": "794750506",
    "status": "Available",
    "isActive": "true",
    "domain": "CORE",
    "type": "CI"
  },
  {
    "name": "160122859",
    "status": "Expired",
    "isActive": "false",
    "domain": "CORE",
    "type": "CI"
  },
  {
    "name": "161884170",
    "status": "Available",
    "isActive": "true",
    "domain": "CORE",
    "type": "CI"
  },
  {
    "name": "227443121",
    "status": "Expired",
    "isActive": "false",
    "domain": "CORE",
    "type": "CI"
  },
  {
    "name": "358513699",
    "status": "Expired",
    "isActive": "false",
    "domain": "CORE",
    "type": "CI"
  },
  {
    "name": "479224775",
    "status": "Available",
    "isActive": "true",
    "domain": "CORE",
    "type": "CI"
  },
  {
    "name": "526684291",
    "status": "InProgress",
    "isActive": "true",
    "domain": "CORE",
    "type": "CI"
  },
  {
    "name": "680602349",
    "status": "InProgress",
    "isActive": "true",
    "domain": "CORE",
    "type": "CI"
  },
  {
    "name": "775385113",
    "status": "Expired",
    "isActive": "false",
    "domain": "CORE",
    "type": "CI"
  },
  {
    "name": "858108824",
    "status": "Expired",
    "isActive": "false",
    "domain": "CORE",
    "type": "CI"
  },
  {
    "name": "200389403",
    "status": "Expired",
    "isActive": "false",
    "domain": "HOTFIX",
    "type": "CI"
  },
  {
    "name": "200910129",
    "status": "Available",
    "isActive": "true",
    "domain": "HOTFIX",
    "type": "CI"
  },
  {
    "name": "233579287",
    "status": "Expired",
    "isActive": "false",
    "domain": "HOTFIX",
    "type": "CI"
  },
  {
    "name": "455346601",
    "status": "Expired",
    "isActive": "false",
    "domain": "HOTFIX",
    "type": "CI"
  },
  {
    "name": "600505941",
    "status": "Expired",
    "isActive": "false",
    "domain": "HOTFIX",
    "type": "CI"
  },
  {
    "name": "864753325",
    "status": "Expired",
    "isActive": "false",
    "domain": "HOTFIX",
    "type": "CI"
  }
]