{
  "321702879": {
    "url": "https://adizatech--321702879.sandbox.my.salesforce.com/secur/frontdoor.jsp?sid=00DF4000004vLyn!ARgAQP_C_TWJm8espih6zz7naMKBV33ZA7hS.IYnNd6z5_uyUB0vnmDcfdDUTbKiqgF70hMDMNJUUMp5KP5td.nsGeLonvBG",
    "username": "azlam@adiza.dev.321702879",
    "orgId": "00DF4000004vLynMAE",
    "issue": "114"
  },
  "811209533": {
    "url": "https://adizatech--811209533.sandbox.my.salesforce.com/secur/frontdoor.jsp?sid=00DF8000000AHnK!AQQAQPmhkiiO3Uaa9rYUjySZzshJrsnL8_2pOPM94g32IPGopG_KtZiw7h9Z_GgJ3xkzzuc3icb.Zy1L9PEnXuKwGNYfcP9q",
    "username": "azlam@adiza.dev.811209533",
    "orgId": "00DF8000000AHnKMAW",
    "issue": "80"
  }
}